mongodb_connector/__init__.py
mongodb_connector/mongo_crud.py
databaseconnectors-0.0.1.dist-info/LICENSE
databaseconnectors-0.0.1.dist-info/METADATA
databaseconnectors-0.0.1.dist-info/WHEEL
databaseconnectors-0.0.1.dist-info/top_level.txt
databaseconnectors-0.0.1.dist-info/RECORD
